airflow_sendgrid_provider/__init__.py
airflow_sendgrid_provider/mailer.py
airflow_sendgrid_provider_j2-0.0.4.dist-info/LICENSE
airflow_sendgrid_provider_j2-0.0.4.dist-info/METADATA
airflow_sendgrid_provider_j2-0.0.4.dist-info/WHEEL
airflow_sendgrid_provider_j2-0.0.4.dist-info/top_level.txt
airflow_sendgrid_provider_j2-0.0.4.dist-info/RECORD
