Metadata-Version: 2.1
Name: airflow-sendgrid-provider-j2
Version: 0.0.4
Summary: UNKNOWN
Home-page: https://gitlab.netprotect.com/hercules/airflow-sendgrid-provider
License: UNKNOWN
Platform: UNKNOWN
Requires-Python: >=3.6
License-File: LICENSE
Requires-Dist: apache-airflow
Requires-Dist: sendgrid
